cli/__init__.py
cli/aamend_cli.py
cli/aamendp_cli.py
cli/acm_cli.py
cli/acmp_cli.py
cli/amend_cli.py
cli/amendp_cli.py
cli/cam_cli.py
cli/camp_cli.py
gitone/__init__.py
gitone/aamend.py
gitone/aamendp.py
gitone/acm.py
gitone/acmp.py
gitone/amend.py
gitone/amendp.py
gitone/cam.py
gitone/camp.py
gitone/spa.py
gitone/spp.py
gitone-0.1.3.dist-info/AUTHORS.rst
gitone-0.1.3.dist-info/LICENSE
gitone-0.1.3.dist-info/METADATA
gitone-0.1.3.dist-info/WHEEL
gitone-0.1.3.dist-info/entry_points.txt
gitone-0.1.3.dist-info/top_level.txt
gitone-0.1.3.dist-info/RECORD
