Metadata-Version: 2.1
Name: gitone
Version: 0.1.3
Summary: Combine multiple git version controls steps into one.
Home-page: https://github.com/marskar/gitone
Author: Martin Skarzynski
Author-email: marskar@gmail.com
License: MIT license
Keywords: gitone
Platform: UNKNOWN
Classifier: Development Status :: 4 - Beta
Classifier: Intended Audience :: Developers
Classifier: License :: OSI Approved :: MIT License
Classifier: Natural Language :: English
Classifier: Programming Language :: Python :: 3.6
Classifier: Programming Language :: Python :: 3.7
Requires-Dist: Click (>=6.0)
Requires-Dist: GitPython (>=2.1.11)
